<LEVELS>
  <LEVEL>
    <LEVEL_ID>0</LEVEL_ID>
    <LEVEL_NAME>level 0</LEVEL_NAME>
    <BACKGROUND_ID>0</BACKGROUND_ID>
    <OBJECTS>
      <OBJECT>
        <OBJECT_ID>0</OBJECT_ID>
        <OBJECT_NAME>golf ball</OBJECT_NAME>
        <SPRITE_ID>0</SPRITE_ID>
        <OBJECT_SHAPE>
          <CIRCLE>
            <RADIUS>75</RADIUS>
          </CIRCLE>
        </OBJECT_SHAPE>
        <OBJECT_VISIBLE>yes</OBJECT_VISIBLE>
        <START_POS>
          <X>479</X>
          <Y>247</Y>
        </START_POS>
        <START_VEL>
          <X>1</X>
          <Y>1</Y>
        </START_VEL>
        <START_ACC>
          <X>0</X>
          <Y>0</Y>
        </START_ACC>
      </OBJECT>
      <OBJECT>
        <OBJECT_ID>1</OBJECT_ID>
        <OBJECT_NAME>paddle vertical</OBJECT_NAME>
        <SPRITE_ID>2</SPRITE_ID>
        <OBJECT_SHAPE>
          <RECTANGLE>
            <SIZE>
              <WIDTH>50</WIDTH>
              <HEIGHT>400</HEIGHT>
            </SIZE>
          </RECTANGLE>
        </OBJECT_SHAPE>
        <OBJECT_VISIBLE>yes</OBJECT_VISIBLE>
        <START_POS>
          <X>98</X>
          <Y>151</Y>
        </START_POS>
        <START_VEL>
          <X>0</X>
          <Y>0</Y>
        </START_VEL>
        <START_ACC>
          <X>0</X>
          <Y>0</Y>
        </START_ACC>
      </OBJECT>
      <OBJECT>
        <OBJECT_ID>2</OBJECT_ID>
        <OBJECT_NAME>paddle vertical</OBJECT_NAME>
        <SPRITE_ID>2</SPRITE_ID>
        <OBJECT_SHAPE>
          <RECTANGLE>
            <SIZE>
              <WIDTH>50</WIDTH>
              <HEIGHT>400</HEIGHT>
            </SIZE>
          </RECTANGLE>
        </OBJECT_SHAPE>
        <OBJECT_VISIBLE>yes</OBJECT_VISIBLE>
        <START_POS>
          <X>1008</X>
          <Y>164</Y>
        </START_POS>
        <START_VEL>
          <X>0</X>
          <Y>0</Y>
        </START_VEL>
        <START_ACC>
          <X>0</X>
          <Y>0</Y>
        </START_ACC>
      </OBJECT>
    </OBJECTS>
    <EVENTS>
      <EVENT>
        <EVENT_ID>0</EVENT_ID>
        <EVENT_TYPE>
          <STEP/>
        </EVENT_TYPE>
        <ACTIONS></ACTIONS>
      </EVENT>
      <EVENT>
        <EVENT_ID>1</EVENT_ID>
        <EVENT_TYPE>
          <BOUNDARY>
            <OBJECT_ID>0</OBJECT_ID>
            <LEVEL_ID>0</LEVEL_ID>
            <EDGES>top</EDGES>
            <ALLOW_OVERLAP>no</ALLOW_OVERLAP>
          </BOUNDARY>
        </EVENT_TYPE>
        <ACTIONS>
          <ACTION>
            <ACTION_ID>0</ACTION_ID>
            <ACTION_TYPE>
              <REFLECT>
                <OBJECT_ID>0</OBJECT_ID>
                <SURFACE_LEVEL_ID>0</SURFACE_LEVEL_ID>
              </REFLECT>
            </ACTION_TYPE>
          </ACTION>
        </ACTIONS>
      </EVENT>
      <EVENT>
        <EVENT_ID>2</EVENT_ID>
        <EVENT_TYPE>
          <BOUNDARY>
            <OBJECT_ID>0</OBJECT_ID>
            <LEVEL_ID>0</LEVEL_ID>
            <EDGES>bottom</EDGES>
            <ALLOW_OVERLAP>no</ALLOW_OVERLAP>
          </BOUNDARY>
        </EVENT_TYPE>
        <ACTIONS>
          <ACTION>
            <ACTION_ID>0</ACTION_ID>
            <ACTION_TYPE>
              <REFLECT>
                <OBJECT_ID>0</OBJECT_ID>
                <SURFACE_LEVEL_ID>0</SURFACE_LEVEL_ID>
              </REFLECT>
            </ACTION_TYPE>
          </ACTION>
        </ACTIONS>
      </EVENT>
      <EVENT>
        <EVENT_ID>3</EVENT_ID>
        <EVENT_TYPE>
          <BOUNDARY>
            <OBJECT_ID>0</OBJECT_ID>
            <LEVEL_ID>0</LEVEL_ID>
            <EDGES>left</EDGES>
            <ALLOW_OVERLAP>no</ALLOW_OVERLAP>
          </BOUNDARY>
        </EVENT_TYPE>
        <ACTIONS>
          <ACTION>
            <ACTION_ID>0</ACTION_ID>
            <ACTION_TYPE>
              <CHANGE_SPRITE>
                <OBJECT_ID>0</OBJECT_ID>
                <SPRITE_ID>1</SPRITE_ID>
              </CHANGE_SPRITE>
            </ACTION_TYPE>
          </ACTION>
        </ACTIONS>
      </EVENT>
      <EVENT>
        <EVENT_ID>4</EVENT_ID>
        <EVENT_TYPE>
          <BOUNDARY>
            <OBJECT_ID>0</OBJECT_ID>
            <LEVEL_ID>0</LEVEL_ID>
            <EDGES>right</EDGES>
            <ALLOW_OVERLAP>no</ALLOW_OVERLAP>
          </BOUNDARY>
        </EVENT_TYPE>
        <ACTIONS>
          <ACTION>
            <ACTION_ID>0</ACTION_ID>
            <ACTION_TYPE>
              <CHANGE_SPRITE>
                <OBJECT_ID>0</OBJECT_ID>
                <SPRITE_ID>0</SPRITE_ID>
              </CHANGE_SPRITE>
            </ACTION_TYPE>
          </ACTION>
        </ACTIONS>
      </EVENT>
      <EVENT>
        <EVENT_ID>5</EVENT_ID>
        <EVENT_TYPE>
          <COLLISION>
            <OBJECT_ID1>0</OBJECT_ID1>
            <OBJECT_ID2>1</OBJECT_ID2>
            <ALLOW_OVERLAP>no</ALLOW_OVERLAP>
          </COLLISION>
        </EVENT_TYPE>
        <ACTIONS>
          <ACTION>
            <ACTION_ID>0</ACTION_ID>
            <ACTION_TYPE>
              <REFLECT>
                <OBJECT_ID>0</OBJECT_ID>
                <SURFACE_OBJECT_ID>1</SURFACE_OBJECT_ID>
              </REFLECT>
            </ACTION_TYPE>
          </ACTION>
        </ACTIONS>
      </EVENT>
      <EVENT>
        <EVENT_ID>6</EVENT_ID>
        <EVENT_TYPE>
          <COLLISION>
            <OBJECT_ID1>0</OBJECT_ID1>
            <OBJECT_ID2>2</OBJECT_ID2>
            <ALLOW_OVERLAP>no</ALLOW_OVERLAP>
          </COLLISION>
        </EVENT_TYPE>
        <ACTIONS>
          <ACTION>
            <ACTION_ID>0</ACTION_ID>
            <ACTION_TYPE>
              <REFLECT>
                <OBJECT_ID>0</OBJECT_ID>
                <SURFACE_OBJECT_ID>2</SURFACE_OBJECT_ID>
              </REFLECT>
            </ACTION_TYPE>
          </ACTION>
        </ACTIONS>
      </EVENT>
      <EVENT>
        <EVENT_ID>7</EVENT_ID>
        <EVENT_TYPE>
          <INPUT>
            <PLAYER_ID>1</PLAYER_ID>
            <VALUE>
              <X>0</X>
              <Y>30</Y>
            </VALUE>
            <TYPE>up</TYPE>
          </INPUT>
        </EVENT_TYPE>
        <ACTIONS>
          <ACTION>
            <ACTION_ID>0</ACTION_ID>
            <ACTION_TYPE>
              <INPUT>
                <OBJECT_ID>1</OBJECT_ID>
                <PLAYER_ID>1</PLAYER_ID>
                <TYPE>add</TYPE>
              </INPUT>
            </ACTION_TYPE>
          </ACTION>
        </ACTIONS>
      </EVENT>
      <EVENT>
        <EVENT_ID>8</EVENT_ID>
        <EVENT_TYPE>
          <INPUT>
            <PLAYER_ID>1</PLAYER_ID>
            <VALUE>
              <X>0</X>
              <Y>30</Y>
            </VALUE>
            <TYPE>down</TYPE>
          </INPUT>
        </EVENT_TYPE>
        <ACTIONS>
          <ACTION>
            <ACTION_ID>0</ACTION_ID>
            <ACTION_TYPE>
              <INPUT>
                <OBJECT_ID>1</OBJECT_ID>
                <PLAYER_ID>1</PLAYER_ID>
                <TYPE>sub</TYPE>
              </INPUT>
            </ACTION_TYPE>
          </ACTION>
        </ACTIONS>
      </EVENT>
      <EVENT>
        <EVENT_ID>9</EVENT_ID>
        <EVENT_TYPE>
          <INPUT>
            <PLAYER_ID>0</PLAYER_ID>
            <VALUE>
              <X>0</X>
              <Y>30</Y>
            </VALUE>
            <TYPE>up</TYPE>
          </INPUT>
        </EVENT_TYPE>
        <ACTIONS>
          <ACTION>
            <ACTION_ID>0</ACTION_ID>
            <ACTION_TYPE>
              <INPUT>
                <OBJECT_ID>2</OBJECT_ID>
                <PLAYER_ID>0</PLAYER_ID>
                <TYPE>add</TYPE>
              </INPUT>
            </ACTION_TYPE>
          </ACTION>
        </ACTIONS>
      </EVENT>
      <EVENT>
        <EVENT_ID>10</EVENT_ID>
        <EVENT_TYPE>
          <INPUT>
            <PLAYER_ID>0</PLAYER_ID>
            <VALUE>
              <X>0</X>
              <Y>30</Y>
            </VALUE>
            <TYPE>down</TYPE>
          </INPUT>
        </EVENT_TYPE>
        <ACTIONS>
          <ACTION>
            <ACTION_ID>0</ACTION_ID>
            <ACTION_TYPE>
              <INPUT>
                <OBJECT_ID>2</OBJECT_ID>
                <PLAYER_ID>0</PLAYER_ID>
                <TYPE>sub</TYPE>
              </INPUT>
            </ACTION_TYPE>
          </ACTION>
        </ACTIONS>
      </EVENT>
    </EVENTS>
  </LEVEL>
</LEVELS>
